README
setup.py
hglock/__init__.py
hglock/pushkeyrpc.py
hglock/unrepr.py
hglock.egg-info/PKG-INFO
hglock.egg-info/SOURCES.txt
hglock.egg-info/dependency_links.txt
hglock.egg-info/not-zip-safe
hglock.egg-info/top_level.txt