Metadata-Version: 1.0
Name: hglock
Version: 0.5.3
Summary: This extension implements a centralized file-based locking scheme for Mercurial.
Home-page: https://bitbucket.org/lantiq/hglock
Author: Lantiq
Author-email: MUC-LQ-ADM-HG-U@lantiq.com
License: GNU GPLv2+
Keywords: mercurial locking
Platform: UNKNOWN
Classifier: Development Status :: 4 - Beta
Classifier: Environment :: Console
Classifier: Intended Audience :: Developers
Classifier: License :: OSI Approved :: GNU General Public License (GPL)
Classifier: Operating System :: OS Independent
Classifier: Programming Language :: Python
Classifier: Topic :: Software Development :: Version Control
